fastapi_simple_redis_cache/NaiveCache.py
fastapi_simple_redis_cache/__init__.py
fastapi_simple_redis_cache-2.0.0.dist-info/METADATA
fastapi_simple_redis_cache-2.0.0.dist-info/WHEEL
fastapi_simple_redis_cache-2.0.0.dist-info/RECORD
